[
  {
    "columnName": "id",
    "dataType": "integer",
    "dtdIdentifier": "1",
    "isGenerated": "NEVER",
    "isIdentity": "NO",
    "isNullable": "YES",
    "isSelfReferencing": "NO",
    "isUpdatable": "YES",
    "numericPrecision": 32,
    "numericPrecisionRadix": 2,
    "numericScale": 0,
    "ordinalPosition": 1,
    "tableCatalog": "db_tpcds",
    "tableName": "table1",
    "tableSchema": "public",
    "udtCatalog": "db_tpcds",
    "udtSchema": "pg_catalog"
  },
  {
    "characterMaximumLength": 6,
    "characterOctetLength": 24,
    "columnName": "a",
    "dataType": "character",
    "dtdIdentifier": "2",
    "isGenerated": "NEVER",
    "isIdentity": "NO",
    "isNullable": "YES",
    "isSelfReferencing": "NO",
    "isUpdatable": "YES",
    "ordinalPosition": 2,
    "tableCatalog": "db_tpcds",
    "tableName": "table1",
    "tableSchema": "public",
    "udtCatalog": "db_tpcds",
    "udtSchema": "pg_catalog"
  },
  {
    "characterMaximumLength": 6,
    "characterOctetLength": 24,
    "columnName": "b",
    "dataType": "character varying",
    "dtdIdentifier": "3",
    "isGenerated": "NEVER",
    "isIdentity": "NO",
    "isNullable": "YES",
    "isSelfReferencing": "NO",
    "isUpdatable": "YES",
    "ordinalPosition": 3,
    "tableCatalog": "db_tpcds",
    "tableName": "table1",
    "tableSchema": "public",
    "udtCatalog": "db_tpcds",
    "udtSchema": "pg_catalog"
  },
  {
    "characterMaximumLength": 6,
    "characterOctetLength": 24,
    "columnName": "c",
    "dataType": "character varying",
    "dtdIdentifier": "4",
    "isGenerated": "NEVER",
    "isIdentity": "NO",
    "isNullable": "YES",
    "isSelfReferencing": "NO",
    "isUpdatable": "YES",
    "ordinalPosition": 4,
    "tableCatalog": "db_tpcds",
    "tableName": "table1",
    "tableSchema": "public",
    "udtCatalog": "db_tpcds",
    "udtSchema": "pg_catalog"
  }
]
